<annotation>
  <folder/>
  <filename>e7e7e7e7e7cb0900.jpg</filename>
  <database/>
  <annotation/>
  <image/>
  <size>
    <height>586</height>
    <width>880</width>
    <depth>3</depth>
  </size>
  <segmented/>
  <object>
    <name>with_mask</name>
    <pose/>
    <truncated/>
    <difficult/>
    <bndbox>
      <xmin>335.79277966650477</xmin>
      <ymin>129.17419459284437</ymin>
      <xmax>531.6197183098592</xmax>
      <ymax>359.2394366197184</ymax>
    </bndbox>
  </object>
</annotation>
